{
    "name": "topaz",
    "weight": 30,
    "max_height": 60,
    "min_height": 40,
    "generator": {
        "type": "ga_simple",
        "radius": [
            12,
            12
        ]
    },
    "density": 0.3,
    "vein_populator": {
        "type": "surface_rock",
        "material": "topaz"
    },
    "dimension_filter": [
        "dimension_id:1"
    ],
    "filler": {
        "type": "simple",
        "value": {
            "type": "weight_random",
            "values": [
                {
                    "weight": "50",
                    "value": "ore:topaz"
                },
                {
                    "weight": "50",
                    "value": "ore:blue_topaz"
                }
            ]
        }
    }
}